test_version_powerhouse_helper/Address_Book_Handler.py
test_version_powerhouse_helper/Note.py
test_version_powerhouse_helper/Note_Book_Handler.py
test_version_powerhouse_helper/Snake.py
test_version_powerhouse_helper/Sort_Files.py
test_version_powerhouse_helper/__init__.py
test_version_powerhouse_helper/addressbook.py
test_version_powerhouse_helper/addressbook_data.py
test_version_powerhouse_helper/main.py
test_version_powerhouse_helper/Сalculator.py
beta_test_version_powerhouse_helper_123-1.0.0.dist-info/LICENSE
beta_test_version_powerhouse_helper_123-1.0.0.dist-info/METADATA
beta_test_version_powerhouse_helper_123-1.0.0.dist-info/WHEEL
beta_test_version_powerhouse_helper_123-1.0.0.dist-info/entry_points.txt
beta_test_version_powerhouse_helper_123-1.0.0.dist-info/top_level.txt
beta_test_version_powerhouse_helper_123-1.0.0.dist-info/RECORD
